{"title":"$:/plugins/kookma/thinkup","name":"Thinkup","description":"The Zettelkasten method of note taking with Tiddlywiki","author":"Mohammad Rahmani","version":"0.2.1","core-version":">=5.2.0","source":"","list":"readme license history","plugin-type":"plugin","dependents":"","type":"application/json","text":"{\n    \"tiddlers\": {\n        \"$:/plugins/kookma/thinkup/buttons/side-by-side/close\": {\n            \"title\": \"$:/plugins/kookma/thinkup/buttons/side-by-side/close\",\n            \"caption\": \"{{$:/core/images/close-button}} {{$:/language/Buttons/Close/Caption}}\",\n            \"created\": \"20200525073739149\",\n            \"description\": \"{{$:/language/Buttons/Close/Hint}}\",\n            \"modified\": \"20210831192727015\",\n            \"tags\": \"\",\n            \"type\": \"text/vnd.tiddlywiki\",\n            \"text\": \"\\\\whitespace trim\\n<$button tooltip={{$:/language/Buttons/Close/Hint}} aria-label={{$:/language/Buttons/Close/Caption}} class=<<tv-config-toolbar-class>>>\\n    <$list filter=\\\"[<tv-config-toolbar-icons>match[yes]]\\\">\\n        {{$:/core/images/close-button}}\\n    </$list>\\n    <$list filter=\\\"[<tv-config-toolbar-text>match[yes]]\\\">\\n        <span class=\\\"tc-btn-text\\\">\\n            <$text text={{$:/language/Buttons/Close/Caption}}/>\\n        </span>\\n    </$list>\\n\\n    <$action-setfield $tiddler=\\\"$:/plugins/kookma/thinkup/side-by-side\\\" tags=\\\"\\\" />\\n    <$action-setfield $tiddler=\\\"$:/themes/tiddlywiki/vanilla/metrics/sidebarwidth\\\" text=\\\"350px\\\" />\\n    <!-- <$action-setfield $tiddler=\\\"$:/state/sidebar\\\" text=\\\"no\\\" />  -->\\n    <$action-setfield $tiddler=\\\"$:/state/tab/sidebar--595412856\\\" text=\\\"$:/plugins/kookma/thinkup/side-by-side\\\" />\\n    <$action-setfield $tiddler=\\\"$:/plugins/kookma/thinkup/side-by-side\\\" text=\\\"\\\" />\\n</$button>\"\n        },\n        \"$:/plugins/kookma/thinkup/buttons/side-by-side/pin\": {\n            \"title\": \"$:/plugins/kookma/thinkup/buttons/side-by-side/pin\",\n            \"caption\": \"{{$:/plugins/kookma/thinkup/images/side-by-side}}{{$:/language/Buttons/Thinkup/Caption/Pin}}\",\n            \"created\": \"20200525050747068\",\n            \"description\": \"{{$:/language/Buttons/Thinkup/Hint/Pin}}\",\n            \"list-before\": \"$:/core/ui/Buttons/close\",\n            \"modified\": \"20210831193421604\",\n            \"tags\": \"$:/tags/ViewToolbar $:/tags/EditToolbar\",\n            \"type\": \"text/vnd.tiddlywiki\",\n            \"text\": \"\\\\whitespace trim\\n\\\\define side-by-side-body()\\n{{$(currentTiddler)$ || $:/plugins/kookma/thinkup/viewtemplates/newxx }}\\n\\\\end\\n\\n\\n\\\\define pinActions()\\n    <$action-setfield $tiddler=\\\"$:/plugins/kookma/thinkup/side-by-side\\\" tags=\\\"$:/tags/SideBar\\\" />\\n\\t\\t<$action-setfield $tiddler=\\\"$:/plugins/kookma/thinkup/side-by-side\\\" caption=\\\"Pinned\\\" />\\n    <$action-setfield $tiddler=\\\"$:/themes/tiddlywiki/vanilla/metrics/sidebarwidth\\\" text=\\\"630px\\\" />\\n    <$action-setfield $tiddler=\\\"$:/state/sidebar\\\" text=\\\"yes\\\" />\\n    <$action-setfield $tiddler=\\\"$:/state/tab/sidebar--595412856\\\" text=\\\"$:/plugins/kookma/thinkup/side-by-side\\\" />\\n    <$action-setfield $tiddler=\\\"$:/plugins/kookma/thinkup/side-by-side\\\" text=<<side-by-side-body>> />\\n\\\\end\\n\\n\\n<$button message=\\\"tm-close-tiddlerxx\\\" tooltip={{$:/language/Buttons/Thinkup/Hint/Pin}} aria-label={{$:/language/Buttons/Thinkup/Caption/Pin}} class=<<tv-config-toolbar-class>>>\\n<$list filter=\\\"[<tv-config-toolbar-icons>match[yes]]\\\">\\n{{$:/plugins/kookma/thinkup/images/side-by-side}}\\n</$list>\\n<$list filter=\\\"[<tv-config-toolbar-text>match[yes]]\\\">\\n<span class=\\\"tc-btn-text\\\">\\n<$text text={{$:/language/Buttons/Thinkup/Caption/Pin}}/>\\n</span>\\n</$list>\\n<<pinActions>>\\n</$button>\\n\\n\"\n        },\n        \"$:/plugins/kookma/thinkup/config/node-explorer\": {\n            \"text\": \"{\\n    \\\"display\\\": \\\"table\\\",\\n    \\\"visibility\\\": \\\"closed\\\",\\n    \\\"tagging\\\": \\\"yes\\\",\\n    \\\"backlinks\\\": \\\"yes\\\",\\n    \\\"transclusion\\\": \\\"yes\\\",\\n    \\\"links\\\": \\\"yes\\\"\\n}\",\n            \"type\": \"application/json\",\n            \"created\": \"20210803175705000\",\n            \"modified\": \"20210907184618375\",\n            \"title\": \"$:/plugins/kookma/thinkup/config/node-explorer\"\n        },\n        \"$:/plugins/kookma/thinkup/history\": {\n            \"title\": \"$:/plugins/kookma/thinkup/history\",\n            \"created\": \"20210512185940326\",\n            \"modified\": \"20210831175821264\",\n            \"tags\": \"\",\n            \"type\": \"text/vnd.tiddlywiki\",\n            \"text\": \"Full change log  https://kookma.github.io/TW-Thinkup/#ChangeLog\\n\\n* ''0.2.0'' -- 2021.08.31 -- added tag clouds\\n* ''0.1.0'' -- 2021.06.01 -- preliminary edition\\n\"\n        },\n        \"$:/plugins/kookma/thinkup/images/beaker\": {\n            \"title\": \"$:/plugins/kookma/thinkup/images/beaker\",\n            \"caption\": \"beaker-plus-outline\",\n            \"collection\": \"\",\n            \"created\": \"20210507151145624\",\n            \"library\": \"Templarian Material Design\",\n            \"library_version\": \"5.9.55\",\n            \"modified\": \"20210512193118450\",\n            \"tags\": \"\",\n            \"type\": \"text/vnd.tiddlywiki\",\n            \"text\": \"<svg width=\\\"22pt\\\" height=\\\"22pt\\\" class=\\\"tc-image-tmd-beaker-plus-outline tc-image-button\\\" viewBox=\\\"0 0 24 24\\\"><path d=\\\"M18 14H20V17H23V19H20V22H18V19H15V17H18V14M3 3H21V5C19.9 5 19 5.9 19 7V12C18.3 12 17.63 12.12 17 12.34V5H7V7H12V8H7V9H10V10H7V11H10V12H7V13H12V14H7V15H10V16H7V19H13.08C13.2 19.72 13.45 20.39 13.8 21H7C5.9 21 5 20.11 5 19V7C5 5.9 4.11 5 3 5V3Z\\\" /></svg>\"\n        },\n        \"$:/plugins/kookma/thinkup/images/bookshelf\": {\n            \"title\": \"$:/plugins/kookma/thinkup/images/bookshelf\",\n            \"caption\": \"bookshelf\",\n            \"collection\": \"\",\n            \"created\": \"20210507151145654\",\n            \"library\": \"Templarian Material Design\",\n            \"library_version\": \"5.9.55\",\n            \"modified\": \"20210512193127450\",\n            \"tags\": \"\",\n            \"type\": \"text/vnd.tiddlywiki\",\n            \"text\": \"<svg width=\\\"22pt\\\" height=\\\"22pt\\\" class=\\\"tc-image-tmd-bookshelf tc-image-button\\\" viewBox=\\\"0 0 24 24\\\"><path d=\\\"M9 3V18H12V3H9M12 5L16 18L19 17L15 4L12 5M5 5V18H8V5H5M3 19V21H21V19H3Z\\\" /></svg>\"\n        },\n        \"$:/plugins/kookma/thinkup/images/lightbulb\": {\n            \"title\": \"$:/plugins/kookma/thinkup/images/lightbulb\",\n            \"caption\": \"lightbulb-on-outline\",\n            \"collection\": \"\",\n            \"created\": \"20210507151145661\",\n            \"library\": \"Templarian Material Design\",\n            \"library_version\": \"5.9.55\",\n            \"modified\": \"20210512193138042\",\n            \"tags\": \"\",\n            \"type\": \"text/vnd.tiddlywiki\",\n            \"text\": \"<svg width=\\\"22pt\\\" height=\\\"22pt\\\" class=\\\"tc-image-tmd-lightbulb-on-outline tc-image-button\\\" viewBox=\\\"0 0 24 24\\\"><path d=\\\"M20,11H23V13H20V11M1,11H4V13H1V11M13,1V4H11V1H13M4.92,3.5L7.05,5.64L5.63,7.05L3.5,4.93L4.92,3.5M16.95,5.63L19.07,3.5L20.5,4.93L18.37,7.05L16.95,5.63M12,6A6,6 0 0,1 18,12C18,14.22 16.79,16.16 15,17.2V19A1,1 0 0,1 14,20H10A1,1 0 0,1 9,19V17.2C7.21,16.16 6,14.22 6,12A6,6 0 0,1 12,6M14,21V22A1,1 0 0,1 13,23H11A1,1 0 0,1 10,22V21H14M11,18H13V15.87C14.73,15.43 16,13.86 16,12A4,4 0 0,0 12,8A4,4 0 0,0 8,12C8,13.86 9.27,15.43 11,15.87V18Z\\\" /></svg>\"\n        },\n        \"$:/plugins/kookma/thinkup/images/list-status\": {\n            \"title\": \"$:/plugins/kookma/thinkup/images/list-status\",\n            \"caption\": \"list-status\",\n            \"collection\": \"\",\n            \"created\": \"20210507185109803\",\n            \"library\": \"Templarian Material Design\",\n            \"library_version\": \"5.9.55\",\n            \"modified\": \"20210512193151032\",\n            \"tags\": \"\",\n            \"type\": \"text/vnd.tiddlywiki\",\n            \"text\": \"<svg width=\\\"22pt\\\" height=\\\"22pt\\\" class=\\\"tc-image-tmd-list-status tc-image-button\\\" viewBox=\\\"0 0 24 24\\\"><path d=\\\"M16.5 11L13 7.5L14.4 6.1L16.5 8.2L20.7 4L22.1 5.4L16.5 11M11 7H2V9H11V7M21 13.4L19.6 12L17 14.6L14.4 12L13 13.4L15.6 16L13 18.6L14.4 20L17 17.4L19.6 20L21 18.6L18.4 16L21 13.4M11 15H2V17H11V15Z\\\" /></svg>\"\n        },\n        \"$:/plugins/kookma/thinkup/images/question\": {\n            \"title\": \"$:/plugins/kookma/thinkup/images/question\",\n            \"caption\": \"account-question-outline\",\n            \"collection\": \"\",\n            \"created\": \"20210507151145637\",\n            \"library\": \"Templarian Material Design\",\n            \"library_version\": \"5.9.55\",\n            \"modified\": \"20210512193204157\",\n            \"tags\": \"\",\n            \"type\": \"text/vnd.tiddlywiki\",\n            \"text\": \"<svg width=\\\"22pt\\\" height=\\\"22pt\\\" class=\\\"tc-image-tmd-account-question-outline tc-image-button\\\" viewBox=\\\"0 0 24 24\\\"><path d=\\\"M20.5,14.5V16H19V14.5H20.5M18.5,9.5H17V9A3,3 0 0,1 20,6A3,3 0 0,1 23,9C23,9.97 22.5,10.88 21.71,11.41L21.41,11.6C20.84,12 20.5,12.61 20.5,13.3V13.5H19V13.3C19,12.11 19.6,11 20.59,10.35L20.88,10.16C21.27,9.9 21.5,9.47 21.5,9A1.5,1.5 0 0,0 20,7.5A1.5,1.5 0 0,0 18.5,9V9.5M9,13C11.67,13 17,14.34 17,17V20H1V17C1,14.34 6.33,13 9,13M9,4A4,4 0 0,1 13,8A4,4 0 0,1 9,12A4,4 0 0,1 5,8A4,4 0 0,1 9,4M9,14.9C6.03,14.9 2.9,16.36 2.9,17V18.1H15.1V17C15.1,16.36 11.97,14.9 9,14.9M9,5.9A2.1,2.1 0 0,0 6.9,8A2.1,2.1 0 0,0 9,10.1A2.1,2.1 0 0,0 11.1,8A2.1,2.1 0 0,0 9,5.9Z\\\" /></svg>\"\n        },\n        \"$:/plugins/kookma/thinkup/images/side-by-side\": {\n            \"title\": \"$:/plugins/kookma/thinkup/images/side-by-side\",\n            \"created\": \"20200525050148795\",\n            \"modified\": \"20210803191734550\",\n            \"type\": \"text/vnd.tiddlywiki\",\n            \"text\": \"<svg class=\\\"tc-image tc-image-button\\\" width=\\\"22pt\\\" height=\\\"22pt\\\" viewBox=\\\"0 0 357.5 412\\\" enable-background=\\\"new 0 0 512 512\\\" style=\\\"transform: scaleX(-1);\\\">\\n<path\\n   clip-path=\\\"none\\\"\\n   d=\\\"M 71.8125,0 0,71.6875 l 71.8125,71.7188 0,-35.4375 c 0.001,0.001 93.11575,-0.8691 144.59375,54.25 C 192.22625,56.9228 71.8125,35.4063 71.8125,35.4063 L 71.8125,0 z m 92.71875,40.9688 c 15.678,10.654 29.3675,22.7272 40.9375,36.0312 L 321.5,77 l 0,298.9688 -149.875,0 c -53.005,0 -31.5,-68.5313 -31.5,-68.5313 0,0 -70.1875,22.7805 -70.1875,-34.0625 l 0,-89.4687 C 40.6515,154.6683 50.51425,164.5488 33.90625,147.9688 l 0,128.5312 c 0,55.295 75.8005,135.5 137.1875,135.5 l 186.40625,0 0,-371.0312 -192.96875,0 z M 108.375,182.625 l 0,27.0313 174.6875,0 0,-27.0313 -174.6875,0 z m -0.0313,58.9063 0,27.0312 174.71875,0 0,-27.0312 -174.71875,0 z\\\"/>\\n</svg>\\n\"\n        },\n        \"$:/plugins/kookma/thinkup/images/tag-text-outline\": {\n            \"title\": \"$:/plugins/kookma/thinkup/images/tag-text-outline\",\n            \"caption\": \"tag-text-outline\",\n            \"collection\": \"\",\n            \"created\": \"20210831143053333\",\n            \"library\": \"Templarian Material Design\",\n            \"library_version\": \"5.9.55\",\n            \"modified\": \"20210831143124713\",\n            \"tags\": \"\",\n            \"type\": \"text/vnd.tiddlywiki\",\n            \"text\": \"<svg width=\\\"22pt\\\" height=\\\"22pt\\\" class=\\\"tc-image-tmd-tag-text-outline tc-image-button\\\" viewBox=\\\"0 0 24 24\\\"><path d=\\\"M21.4 11.6L12.4 2.6C12 2.2 11.5 2 11 2H4C2.9 2 2 2.9 2 4V11C2 11.5 2.2 12 2.6 12.4L11.6 21.4C12 21.8 12.5 22 13 22C13.5 22 14 21.8 14.4 21.4L21.4 14.4C21.8 14 22 13.5 22 13C22 12.5 21.8 12 21.4 11.6M13 20L4 11V4H11L20 13M6.5 5C7.3 5 8 5.7 8 6.5S7.3 8 6.5 8 5 7.3 5 6.5 5.7 5 6.5 5M10.1 8.9L11.5 7.5L17 13L15.6 14.4L10.1 8.9M7.6 11.4L9 10L13 14L11.6 15.4L7.6 11.4Z\\\" /></svg>\"\n        },\n        \"$:/plugins/kookma/thinkup/license\": {\n            \"title\": \"$:/plugins/kookma/thinkup/license\",\n            \"created\": \"20210512185940326\",\n            \"modified\": \"20210512185944733\",\n            \"tags\": \"\",\n            \"type\": \"text/vnd.tiddlywiki\",\n            \"text\": \"Distributed under an MIT license.\\n\\nCopyright (c) 2021 [[Mohammad Rahmani|https://github.com/kookma]]\\n\\n<<<\\nPermission is hereby granted, free of charge, to any person obtaining a copy of this software and associated documentation files (the \\\"Software\\\"), to deal in the Software without restriction, including without limitation the rights to use, copy, modify, merge, publish, distribute, sublicense, and/or sell copies of the Software, and to permit persons to whom the Software is furnished to do so, subject to the following conditions:\\n\\nThe above copyright notice and this permission notice shall be included in all copies or substantial portions of the Software.\\n\\nTHE SOFTWARE IS PROVIDED \\\"AS IS\\\", WITHOUT WARRANTY OF ANY KIND, EXPRESS OR IMPLIED, INCLUDING BUT NOT LIMITED TO THE WARRANTIES OF MERCHANTABILITY, FITNESS FOR A PARTICULAR PURPOSE AND NONINFRINGEMENT. IN NO EVENT SHALL THE AUTHORS OR COPYRIGHT HOLDERS BE LIABLE FOR ANY CLAIM, DAMAGES OR OTHER LIABILITY, WHETHER IN AN ACTION OF CONTRACT, TORT OR OTHERWISE, ARISING FROM, OUT OF OR IN CONNECTION WITH THE SOFTWARE OR THE USE OR OTHER DEALINGS IN THE SOFTWARE.\\n<<<\"\n        },\n        \"$:/plugins/kookma/thinkup/macros/node-explorer\": {\n            \"title\": \"$:/plugins/kookma/thinkup/macros/node-explorer\",\n            \"created\": \"20210801192651059\",\n            \"modified\": \"20210907185546521\",\n            \"tags\": \"\",\n            \"type\": \"text/vnd.tiddlywiki\",\n            \"text\": \"\\\\import [[$:/plugins/kookma/thinkup/macros/utility]]\\n\\n\\\\define xtext-pattern-transclude() {{.*}}\\n\\n\\\\define text-pattern-transclude()\\n{{$(currentTiddler)$.*}}\\n\\\\end\\n\\n\\\\define linksFilter()         [all[current]!is[system]links[]]\\n\\\\define backlinksFilter()     [all[current]!is[system]backlinks[]]\\n\\\\define tagsFilter()          [all[current]!is[system]tagging[]]\\n\\\\define transclusionFilter()  [regexp:text<text-pattern-transclude>]\\n\\n<$set name=mainfilter filter=\\\"[<tidNodeExplorerConfig>getindex[links]match[yes]then<linksFilter>] [<tidNodeExplorerConfig>getindex[backlinks]match[yes]then<backlinksFilter>] [<tidNodeExplorerConfig>getindex[tagging]match[yes]then<tagsFilter>] [<tidNodeExplorerConfig>getindex[transclusion]match[yes]then<transclusionFilter>]\\\">\\n\\n<!--check to see if there is any node -->\\n<$list filter=\\\"[subfilter<mainfilter>] +[count[]compare:number:gteq[1]]\\\" variable=null>\\n\\n<!-- change the srcClass and labelClass to change the feel and look of Node Explorer. For customizing dynamic table, see $:/plugins/kookma/thinkup/ui/node-explorer\\n-->\\n<$macrocall \\n  $name=details \\n  label=\\\"Node Explorer\\\"\\n  status={{{ [<tidNodeExplorerConfig>getindex[visibility]] ~[[open]] }}}\\n  labelClass=\\\"alert alert-secondary py-1 my-2\\\"\\n  srcClass  =\\\"alert border-secondary py-0\\\"\\n  src={{$:/plugins/kookma/thinkup/ui/node-explorer}}\\n  />\\n\\n</$list>\\n</$set>\"\n        },\n        \"$:/plugins/kookma/thinkup/macros/tag-cloud\": {\n            \"title\": \"$:/plugins/kookma/thinkup/macros/tag-cloud\",\n            \"created\": \"20210831144029397\",\n            \"modified\": \"20210831144728179\",\n            \"tags\": \"\",\n            \"type\": \"text/vnd.tiddlywiki\",\n            \"text\": \"\\\\define getTags()\\n<$list filter=\\\"[all[tiddlers]!prefix[$:/]tags[]] +[!prefix[$:/]] $(extra_filter)$\\\">\\n   <$text text=\\\"[[\\\"/>{{{ [<currentTiddler>tagging[]count[]] }}}°≈°<<currentTiddler>><$text text=\\\"]]\\\"/>\\n</$list>\\n\\\\end\\n\\n\\\\define sortTags()\\n<$list filter=\\\"[enlist<items>!sortan[]] :filter[split[°≈°]first[]compare:integer:gteq<__n__>]\\\" >\\n   <$list filter=\\\"[<currentTiddler>split[°≈°]last[]]\\\"><$text text=\\\"[[\\\"/><<currentTiddler>><$text text=\\\"]]\\\"/></$list>\\n</$list>\\n\\\\end\\n\\n\\\\define tagcloud_showbycount(n:5, extrafilter:\\\"\\\")\\n<$vars extra_filter=<<__extrafilter__>> >\\n<$wikify    name=\\\"items\\\"  text=<<getTags>>  >\\n   <$wikify name=\\\"sorted\\\" text=<<sortTags>> >\\n      <$list filter=<<sorted>>>\\n         <$vars count={{{ [<currentTiddler>tagging[]count[]] }}}>\\n          <span class=\\\"kk-tu-sp\\\"><<tag>><sup class=\\\"kk-tu-sup\\\"><<count>></sup></span>\\n         </$vars>\\n      </$list>\\n   </$wikify>\\n</$wikify>\\n</$vars>\\n\\\\end\\n\\n<!--\\n;Original idea\\n: Eric Shulman\\n:http://tiddlytools.com/filtergenerators.html#TiddlyTools%2FFilterGenerators%2FTagCloud\\n-->\\n\\n<!-- 2021.05.21\\nMohammad\\n[FIXED] both system tags and system tiddlers are excluded now!\\n[NEW] only tags with specified number (frequency used)is displayed\\n[NEW] extrafilter parameter like `+[has[color]]` or `-[prefix[exmp]]` can be passed to refine the tags result (this apply on tgas not on tiddlers tagged with something). IMPORTANT: `+` and `-` are mandatory!\\n-->\"\n        },\n        \"$:/plugins/kookma/thinkup/macros/utility\": {\n            \"title\": \"$:/plugins/kookma/thinkup/macros/utility\",\n            \"created\": \"20210803141955154\",\n            \"modified\": \"20210803142046058\",\n            \"tags\": \"\",\n            \"type\": \"text/vnd.tiddlywiki\",\n            \"text\": \"\\\\define tidNodeExplorerConfig() $:/plugins/kookma/thinkup/config/node-explorer\"\n        },\n        \"$:/plugins/kookma/thinkup/readme\": {\n            \"title\": \"$:/plugins/kookma/thinkup/readme\",\n            \"created\": \"20210512185940327\",\n            \"modified\": \"20210512185942636\",\n            \"tags\": \"\",\n            \"type\": \"text/vnd.tiddlywiki\",\n            \"text\": \"; Shiraz[use correct name]\\ndescribe what is the plugin in one paragraph\\n\\n;Code and demo\\nFor learning plugin features, syntax, tutorial and examples see the plugin demo and code pages\\n\\n* Demo: https://kookma.github.io/TW-???/\\n* Code: https://github.com/kookma/TW-???\\n\"\n        },\n        \"$:/plugins/kookma/thinkup/side-by-side\": {\n            \"title\": \"$:/plugins/kookma/thinkup/side-by-side\",\n            \"caption\": \"Pinned\",\n            \"created\": \"20210803195829638\",\n            \"modified\": \"20210907183744864\",\n            \"tags\": \"\",\n            \"type\": \"text/vnd.tiddlywiki\"\n        },\n        \"$:/plugins/kookma/thinkup/styles/node-explorer.css\": {\n            \"title\": \"$:/plugins/kookma/thinkup/styles/node-explorer.css\",\n            \"text\": \"/* reset the KaTeX equation numbering when tiddler is displayed through node explorer inside another tiddler - see Shiraz and KaTeX plugins for details*/\\n\\n.shiraz-dtable-expanded-record{ counter-reset: katexEqnNo; }\\n\\n\\n\",\n            \"created\": \"20210918195951960\",\n            \"modified\": \"20210918200245010\",\n            \"tags\": \"$:/tags/Stylesheet\",\n            \"type\": \"text/css\"\n        },\n        \"$:/plugins/kookma/thinkup/styles/side-by-side.css\": {\n            \"title\": \"$:/plugins/kookma/thinkup/styles/side-by-side.css\",\n            \"created\": \"20200525085622139\",\n            \"modified\": \"20210831192647840\",\n            \"tags\": \"\",\n            \"type\": \"text/vnd.tiddlywiki\",\n            \"text\": \"div.tc-tiddler-body.tc-reveal a.tc-tiddlylink  {\\n   color: <<colour tiddler-link-foreground>>;\\n}\\n\\ndiv.tc-tiddler-body.tc-reveal {\\n\\tcolor: <<colour foreground>>;\\n}\\n\\n/* there is an error with color on plugin page */\"\n        },\n        \"$:/plugins/kookma/thinkup/styles/tag-cloud.css\": {\n            \"title\": \"$:/plugins/kookma/thinkup/styles/tag-cloud.css\",\n            \"text\": \".kk-tu-sp{\\nmargin-bottom:10px;\\ndisplay:inline-block;\\n}\\n\\n.kk-tu-sp2 {\\n  font-size:0.85em;\\n\\tfont-weight:400;\\n\\tcolor:blue;\\n}\",\n            \"created\": \"20210831144440205\",\n            \"modified\": \"20210831144717058\",\n            \"tags\": \"$:/tags/Stylesheet\",\n            \"type\": \"text/css\"\n        },\n        \"$:/plugins/kookma/thinkup/templates/sidebar\": {\n            \"title\": \"$:/plugins/kookma/thinkup/templates/sidebar\",\n            \"created\": \"20210425110058007\",\n            \"modified\": \"20210512190851324\",\n            \"tags\": \"\",\n            \"type\": \"text/vnd.tiddlywiki\",\n            \"text\": \"\\\\define createItem()\\n  <$action-sendmessage \\n    $message=\\\"tm-new-tiddler\\\" \\n    title=<<unusedtitle \\\"\\\"\\\"New $(new-item-title)$\\\"\\\"\\\">> \\n    tags=\\\"[[$(currentTiddler)$]]\\\" \\n    text=<<now \\\"Today is DDth, MMM YYYY\\\">>\\n  />\\n\\\\end\\n\\n\\n\\\\define newItem()\\n<$vars new-item-title={{{ [<currentTiddler>removesuffix[s]] ~[<currentTiddler>] }}}>\\n<$button actions=<<createItem>> class=\\\"btn btn-sm\\\" >\\nNew <<new-item-title>>\\n</$button>\\n</$vars>\\n\\\\end\\n\\n<$tiddler tiddler=<<currentTab>>>\\n<div class=\\\"float-right\\\" style=\\\"margin-right:20px;\\\">\\n<<newItem>>\\n</div>\\n\\n<$list filter=\\\"[tag<currentTiddler>]\\\" template=\\\"$:/core/ui/ListItemTemplate\\\"/>\\n</$tiddler>\\n\"\n        },\n        \"$:/plugins/kookma/thinkup/ui/ControlPanel/Settings\": {\n            \"title\": \"$:/plugins/kookma/thinkup/ui/ControlPanel/Settings\",\n            \"caption\": \"Thinkup\",\n            \"created\": \"20210801161108093\",\n            \"list-after\": \"$:/core/ui/ControlPanel/Settings/TiddlyWiki\",\n            \"modified\": \"20210907184418636\",\n            \"tags\": \"$:/tags/ControlPanel/SettingsTab $:/tags/MoreSideBar\",\n            \"type\": \"text/vnd.tiddlywiki\",\n            \"text\": \"\\\\import [[$:/plugins/kookma/thinkup/macros/utility]]\\n\\nThese settings let you customise the behaviour of Thinkup plugin.\\n\\n---\\n\\n;Show Thinkup setting in more sidebar\\n:<$checkbox tiddler=\\\"$:/plugins/kookma/thinkup/ui/ControlPanel/Settings\\\" tag=\\\"$:/tags/MoreSideBar\\\"> Show setting in more sidebar</$checkbox>\\n\\n---\\n\\n;Node explorer switch\\n:<$checkbox tiddler=\\\"$:/state/thinkup/show-node-explorer\\\" field=\\\"text\\\" checked=hide> Disable node explorer</$checkbox>\\n\\n<$reveal type=match stateTitle=\\\"$:/state/thinkup/show-node-explorer\\\" stateField=\\\"text\\\" text=\\\"show\\\" default=show>\\n\\n;Node filters (show/hide in node explorer)\\n:<$checkbox tiddler=<<tidNodeExplorerConfig>> index=\\\"links\\\"         checked=yes> links</$checkbox>\\n:<$checkbox tiddler=<<tidNodeExplorerConfig>> index=\\\"backlinks\\\"     checked=yes> backlinks</$checkbox>\\n:<$checkbox tiddler=<<tidNodeExplorerConfig>> index=\\\"tagging\\\"       checked=yes> tagging</$checkbox>\\n:<$checkbox tiddler=<<tidNodeExplorerConfig>> index=\\\"transclusion\\\"  checked=yes> transclusion</$checkbox>\\n\\n;Node explorer display format\\n:<$radio tiddler=<<tidNodeExplorerConfig>> index=\\\"display\\\"  value=table> dynamic table   </$radio>\\n:<$radio tiddler=<<tidNodeExplorerConfig>> index=\\\"display\\\"  value=flat > simple flat list</$radio>\\n\\n;Default content visibility\\n:<$radio tiddler=<<tidNodeExplorerConfig>> index=\\\"visibility\\\"  value=closed > closed </$radio>\\n:<$radio tiddler=<<tidNodeExplorerConfig>> index=\\\"visibility\\\"  value=open   > open   </$radio>\\n</$reveal>\"\n        },\n        \"$:/plugins/kookma/thinkup/ui/node-explorer\": {\n            \"title\": \"$:/plugins/kookma/thinkup/ui/node-explorer\",\n            \"created\": \"20210801184619692\",\n            \"modified\": \"20210803153028486\",\n            \"tags\": \"\",\n            \"type\": \"text/vnd.tiddlywiki\",\n            \"text\": \"<!-- use dynamic table format for nodes-->\\n<$reveal type=match stateTitle=<<tidNodeExplorerConfig>> stateIndex=display default=table text=table tag=div>\\n<$macrocall $name=table-dynamic \\n  filter=<<mainfilter>>\\n  fields=\\\"tbl-expand title tbl-linktype tags created\\\" \\n  class=\\\"w-100\\\"\\n  editButton=no\\n/>\\n</$reveal>\\n\\n<!-- use simple flat format for nodes-->\\n<$reveal type=nomatch stateTitle=<<tidNodeExplorerConfig>> stateIndex=display default=table text=table tag=div>\\n<$list filter=\\\"[subfilter<mainfilter>sort[title]butlast[]]\\\"><$link/> | </$list>\\n<$list filter=\\\"[subfilter<mainfilter>sort[title]last[]]\\\"><$link/></$list>\\n</$reveal>\"\n        },\n        \"$:/plugins/kookma/thinkup/ui/sidebar\": {\n            \"title\": \"$:/plugins/kookma/thinkup/ui/sidebar\",\n            \"caption\": \"Thinkup\",\n            \"created\": \"20210425103526384\",\n            \"list\": \"Ideas Questions Experiments Bibliography ToDo\",\n            \"modified\": \"20210831192545988\",\n            \"tags\": \"$:/tags/SideBar\",\n            \"type\": \"text/vnd.tiddlywiki\",\n            \"text\": \"<small>Think Up: Use one's ingenuity to invent or devise something [[Lexico|https://www.lexico.com/definition/think_up]]</small>\\n<$macrocall $name=tabs tabsList=\\\"[all[tiddlers+shadows]tag[$:/tags/Thinkup]!has[draft.of]]\\\" default=\\\"Ideas\\\" class=\\\"tc-vertical\\\"/>\"\n        },\n        \"$:/plugins/kookma/thinkup/viewtemplates/newxx\": {\n            \"title\": \"$:/plugins/kookma/thinkup/viewtemplates/newxx\",\n            \"created\": \"20210803195528481\",\n            \"modified\": \"20210831192845036\",\n            \"tags\": \"show-content\",\n            \"type\": \"text/vnd.tiddlywiki\",\n            \"text\": \"\\\\define folded-state()\\n$:/state/folded/$(currentTiddler)$\\n\\\\end\\n\\\\define cancel-delete-tiddler-actions(message) <$action-sendmessage $message=\\\"tm-$message$-tiddler\\\"/>\\n\\\\import [all[shadows+tiddlers]tag[$:/tags/Macro/View]!has[draft.of]]\\n<$vars storyTiddler=<<currentTiddler>> tiddlerInfoState=<<qualify \\\"$:/state/popup/tiddler-info\\\">>><div data-tiddler-title=<<currentTiddler>> data-tags={{!!tags}} class={{{ tc-tiddler-frame tc-tiddler-view-frame [<currentTiddler>is[tiddler]then[tc-tiddler-exists]] [<currentTiddler>is[missing]!is[shadow]then[tc-tiddler-missing]] [<currentTiddler>is[shadow]then[tc-tiddler-exists tc-tiddler-shadow]] [<currentTiddler>is[shadow]is[tiddler]then[tc-tiddler-overridden-shadow]] [<currentTiddler>is[system]then[tc-tiddler-system]] [{!!class}] [<currentTiddler>tags[]encodeuricomponent[]addprefix[tc-tagged-]] +[join[ ]] }}}><$list filter=\\\"[list[$:/plugins/kookma/thinkup/viewtemplates/side-by-sidex]] [all[shadows+tiddlers]tag[$:/tags/ViewTemplate]!has[draft.of]] -[[$:/core/ui/ViewTemplate/title]] \\\" variable=\\\"listItem\\\"><$transclude tiddler=<<listItem>>/></$list>\\n</div>\\n</$vars>\\n\"\n        },\n        \"$:/plugins/kookma/thinkup/viewtemplates/node-explorer\": {\n            \"title\": \"$:/plugins/kookma/thinkup/viewtemplates/node-explorer\",\n            \"created\": \"20210501201700405\",\n            \"modified\": \"20210803140751818\",\n            \"tags\": \"$:/tags/ViewTemplate\",\n            \"type\": \"text/vnd.tiddlywiki\",\n            \"text\": \"<$reveal type=match stateTitle=\\\"$:/state/thinkup/show-node-explorer\\\" stateField=text default=show text=show>\\n<$transclude tiddler=\\\"$:/plugins/kookma/thinkup/macros/node-explorer\\\"/>\\n</$reveal>\"\n        },\n        \"$:/plugins/kookma/thinkup/viewtemplates/side-by-side-title\": {\n            \"title\": \"$:/plugins/kookma/thinkup/viewtemplates/side-by-side-title\",\n            \"created\": \"20200525073529278\",\n            \"modified\": \"20210831192727007\",\n            \"type\": \"text/vnd.tiddlywiki\",\n            \"text\": \"\\\\whitespace trim\\n\\\\define title-styles()\\nfill:$(foregroundColor)$;\\n\\\\end\\n\\\\define config-title()\\n$:/config/ViewToolbarButtons/Visibility/$(listItem)$\\n\\\\end\\n<div class=\\\"tc-tiddler-title\\\">\\n<div class=\\\"tc-titlebar\\\">\\n<span class=\\\"tc-tiddler-controls\\\">\\n<$list filter=\\\"$:/plugins/kookma/thinkup/buttons/side-by-side/close\\\" variable=\\\"listItem\\\"><$reveal type=\\\"nomatch\\\" state=<<config-title>> text=\\\"hide\\\"><$set name=\\\"tv-config-toolbar-class\\\" filter=\\\"[<tv-config-toolbar-class>] [<listItem>encodeuricomponent[]addprefix[tc-btn-]]\\\"><$transclude tiddler=<<listItem>>/></$set></$reveal></$list>\\n</span>\\n<$set name=\\\"tv-wikilinks\\\" value={{$:/config/Tiddlers/TitleLinks}}>\\n<$link>\\n<$set name=\\\"foregroundColor\\\" value={{!!color}}>\\n<span class=\\\"tc-tiddler-title-icon\\\" style=<<title-styles>>>\\n<$transclude tiddler={{!!icon}}>\\n<$transclude tiddler={{$:/config/DefaultTiddlerIcon}}/>\\n</$transclude>\\n</span>\\n</$set>\\n<$list filter=\\\"[all[current]removeprefix[$:/]]\\\">\\n<h2 class=\\\"tc-title\\\" title={{$:/language/SystemTiddler/Tooltip}}>\\n<span class=\\\"tc-system-title-prefix\\\">$:/</span><$text text=<<currentTiddler>>/>\\n</h2>\\n</$list>\\n<$list filter=\\\"[all[current]!prefix[$:/]]\\\">\\n<h2 class=\\\"tc-title\\\">\\n<$view field=\\\"title\\\"/>\\n</h2>\\n</$list>\\n</$link>\\n</$set>\\n</div>\\n\\n<$reveal type=\\\"nomatch\\\" text=\\\"\\\" default=\\\"\\\" state=<<tiddlerInfoState>> class=\\\"tc-tiddler-info tc-popup-handle\\\" animate=\\\"yes\\\" retain=\\\"yes\\\">\\n\\n<$list filter=\\\"[all[shadows+tiddlers]tag[$:/tags/TiddlerInfoSegment]!has[draft.of]] [[$:/core/ui/TiddlerInfo]]\\\" variable=\\\"listItem\\\"><$transclude tiddler=<<listItem>> mode=\\\"block\\\"/></$list>\\n\\n</$reveal>\\n</div>\"\n        },\n        \"$:/plugins/kookma/thinkup/viewtemplates/side-by-sidex\": {\n            \"title\": \"$:/plugins/kookma/thinkup/viewtemplates/side-by-sidex\",\n            \"created\": \"20200525074313554\",\n            \"list\": \"$:/plugins/kookma/thinkup/viewtemplates/side-by-side-title $:/core/ui/ViewTemplate/subtitle $:/core/ui/ViewTemplate/tags $:/core/ui/ViewTemplate/classic $:/core/ui/ViewTemplate/body $:/core/ui/ViewTemplate/import $:/core/ui/ViewTemplate/plugin $:/ak/plugins/TWCrossLinks/ui/footer.kwd\",\n            \"modified\": \"20210831192002025\",\n            \"type\": \"text/vnd.tiddlywiki\",\n            \"text\": \"\\\\define folded-state()\\n$:/state/folded/$(currentTiddler)$\\n\\\\end\\n\\n<$vars storyTiddler=<<currentTiddler>> tiddlerInfoState=<<qualify \\\"$:/state/popup/tiddler-info\\\">>><div data-tiddler-title=<<currentTiddler>> data-tags={{!!tags}} class={{{ tc-tiddler-frame tc-tiddler-view-frame [<currentTiddler>is[tiddler]then[tc-tiddler-exists]] [<currentTiddler>is[missing]!is[shadow]then[tc-tiddler-missing]] [<currentTiddler>is[shadow]then[tc-tiddler-exists tc-tiddler-shadow]] [<currentTiddler>is[shadow]is[tiddler]then[tc-tiddler-overridden-shadow]] [<currentTiddler>is[system]then[tc-tiddler-system]] [{!!class}] [<currentTiddler>tags[]encodeuricomponent[]addprefix[tc-tagged-]] +[join[ ]] }}}>\\n    <$list filter=\\\"[list[$:/plugins/kookma/thinkup/viewtemplates/side-by-sidex]]\\\" variable=\\\"listItem\\\"><$transclude tiddler=<<listItem>>/></$list>\\n</div>\\n</$vars>\\n\\n\\n\"\n        }\n    }\n}"}